aries_cloudagent_vsw/__init__.py
aries_cloudagent_vsw/version.py
aries_cloudagent_vsw/admin/__init__.py
aries_cloudagent_vsw/admin/base_server.py
aries_cloudagent_vsw/admin/error.py
aries_cloudagent_vsw/admin/server.py
aries_cloudagent_vsw/admin/tests/__init__.py
aries_cloudagent_vsw/admin/tests/test_admin_server.py
aries_cloudagent_vsw/cache/__init__.py
aries_cloudagent_vsw/cache/base.py
aries_cloudagent_vsw/cache/basic.py
aries_cloudagent_vsw/cache/tests/__init__.py
aries_cloudagent_vsw/cache/tests/test_basic_cache.py
aries_cloudagent_vsw/commands/__init__.py
aries_cloudagent_vsw/commands/help.py
aries_cloudagent_vsw/commands/provision.py
aries_cloudagent_vsw/commands/start.py
aries_cloudagent_vsw/commands/tests/__init__.py
aries_cloudagent_vsw/commands/tests/test_help.py
aries_cloudagent_vsw/commands/tests/test_init.py
aries_cloudagent_vsw/commands/tests/test_provision.py
aries_cloudagent_vsw/commands/tests/test_start.py
aries_cloudagent_vsw/config/__init__.py
aries_cloudagent_vsw/config/argparse.py
aries_cloudagent_vsw/config/base.py
aries_cloudagent_vsw/config/base_context.py
aries_cloudagent_vsw/config/default_context.py
aries_cloudagent_vsw/config/error.py
aries_cloudagent_vsw/config/injection_context.py
aries_cloudagent_vsw/config/injector.py
aries_cloudagent_vsw/config/ledger.py
aries_cloudagent_vsw/config/logging.py
aries_cloudagent_vsw/config/provider.py
aries_cloudagent_vsw/config/settings.py
aries_cloudagent_vsw/config/util.py
aries_cloudagent_vsw/config/wallet.py
aries_cloudagent_vsw/config/tests/__init__.py
aries_cloudagent_vsw/config/tests/test_argparse.py
aries_cloudagent_vsw/config/tests/test_default_context.py
aries_cloudagent_vsw/config/tests/test_injection_context.py
aries_cloudagent_vsw/config/tests/test_injector.py
aries_cloudagent_vsw/config/tests/test_ledger.py
aries_cloudagent_vsw/config/tests/test_logging.py
aries_cloudagent_vsw/config/tests/test_provider.py
aries_cloudagent_vsw/config/tests/test_settings.py
aries_cloudagent_vsw-0.0.3.dist-info/LICENSE
aries_cloudagent_vsw-0.0.3.dist-info/METADATA
aries_cloudagent_vsw-0.0.3.dist-info/NOTICES
aries_cloudagent_vsw-0.0.3.dist-info/WHEEL
aries_cloudagent_vsw-0.0.3.dist-info/top_level.txt
aries_cloudagent_vsw-0.0.3.dist-info/RECORD
